codename_generator/__init__.py
codename_generator/codename_generator.py
codename_generator-1.1.3.dist-info/METADATA
codename_generator-1.1.3.dist-info/WHEEL
codename_generator-1.1.3.dist-info/entry_points.txt
codename_generator-1.1.3.dist-info/top_level.txt
codename_generator-1.1.3.dist-info/RECORD
